melon_music_player-3.0.0a0.dist-info/DESCRIPTION.rst
melon_music_player-3.0.0a0.dist-info/METADATA
melon_music_player-3.0.0a0.dist-info/RECORD
melon_music_player-3.0.0a0.dist-info/WHEEL
melon_music_player-3.0.0a0.dist-info/metadata.json
melon_music_player-3.0.0a0.dist-info/top_level.txt
mpserver/__init__.py
mpserver/config.py
mpserver/datamanager.py
mpserver/datastructures.py
mpserver/interfaces.py
mpserver/mediadownloader.py
mpserver/models.py
mpserver/musicplayer.py
mpserver/musicserver.py
mpserver/tools.py
mpserver/grpc/__init__.py
mpserver/grpc/mmp_pb2.py
mpserver/grpc/mmp_pb2_grpc.py
