Metadata-Version: 2.0
Name: melon-music-player
Version: 3.0.0a0
Summary: A MusicPlayer which can be controlled by different controllers
Home-page: https://melledijkstra.nl
Author: Melle Dijkstra
Author-email: dev.melle@gmail.com
License: MIT
Download-URL: https://github.com/MelleDijkstra/PythonMusicPlayer
Platform: UNKNOWN
Classifier: Development Status :: 3 - Alpha
Classifier: Intended Audience :: End Users/Desktop
Classifier: License :: OSI Approved :: MIT License
Classifier: Programming Language :: Python :: 3
Classifier: Programming Language :: Python :: 3.6
Requires-Dist: typing (==3.6.4)
Requires-Dist: youtube-dl (==2016.12.1)
Requires-Dist: python-vlc (==3.0.101)
Requires-Dist: setuptools (==38.4.0)
Requires-Dist: tinytag (==0.18.0)
Requires-Dist: grpcio (==1.8.4)
Requires-Dist: grpcio-tools (==1.8.4)
Requires-Dist: protobuf (==3.5.1)
Requires-Dist: mutagen (==1.40.0)
